dleamse/__init__.py
dleamse/dleamse_encode_and_embed.py
dleamse/dleamse_faiss_index_search.py
dleamse/dleamse_faiss_index_writer.py
dleamse/dleamse_tests.py
dleamse/mslookup.py
dleamse-0.3.6.data/scripts/mslookup.py
dleamse-0.3.6.dist-info/LICENSE
dleamse-0.3.6.dist-info/METADATA
dleamse-0.3.6.dist-info/WHEEL
dleamse-0.3.6.dist-info/top_level.txt
dleamse-0.3.6.dist-info/RECORD
