Metadata-Version: 2.1
Name: dleamse
Version: 0.3.6
Summary: dleamse's encoding and embedding methods, and dleamse's faiss index (IndexIDMap type) write.
Home-page: https://github.com/bigbio/DLEAMSE
Author: BigBio Team
Author-email: qinchunyuan1995@gmail.com
License: 'Apache 2.0
Platform: any
Classifier: Programming Language :: Python :: 3
Classifier: License :: OSI Approved :: Apache Software License
Classifier: Operating System :: OS Independent
Classifier: Topic :: Scientific/Engineering :: Bio-Informatics
Requires-Python: >3.5
Requires-Dist: numba (>=0.45)
Requires-Dist: numpy (>=1.13.3)
Requires-Dist: pyteomics (>=3.5.1)
Requires-Dist: torch (==1.0.0)
Requires-Dist: faiss-cpu (>=1.5.3)
Requires-Dist: more-itertools (==7.1.0)
